MANIFEST.in
README
setup.py
demo/__init__.py
demo/manage.py
demo/settings.py
demo/test.py
demo/urls.py
demo/urlauth/__init__.py
demo/urlauth/admin.py
demo/urlauth/middleware.py
demo/urlauth/models.py
demo/urlauth/settings.py
demo/urlauth/signals.py
demo/urlauth/tests.py
demo/urlauth/util.py
demo/urlauth/management/__init__.py
demo/urlauth/management/commands/__init__.py
demo/urlauth/management/commands/urlauth_cleanup.py
demo/urlauth/migrations/0001_initial.py
demo/urlauth/migrations/0002_auto__chg_field_authkey_uid.py
demo/urlauth/migrations/__init__.py
django_urlauth.egg-info/PKG-INFO
django_urlauth.egg-info/SOURCES.txt
django_urlauth.egg-info/dependency_links.txt
django_urlauth.egg-info/top_level.txt
urlauth/__init__.py
urlauth/admin.py
urlauth/middleware.py
urlauth/models.py
urlauth/settings.py
urlauth/signals.py
urlauth/tests.py
urlauth/util.py
urlauth/management/__init__.py
urlauth/management/commands/__init__.py
urlauth/management/commands/urlauth_cleanup.py
urlauth/migrations/0001_initial.py
urlauth/migrations/0002_auto__chg_field_authkey_uid.py
urlauth/migrations/__init__.py