Metadata-Version: 1.0
Name: django-urlauth
Version: 0.1.8
Summary: Django application for user authentication with key in hypertext link
Home-page: http://bitbucket.org/lorien/django-urlauth/
Author: Grigoriy Petukhov
Author-email: lorien@lorien.name
License: BSD
Keywords: django application authentication authorization
Platform: UNKNOWN
Classifier: Development Status :: 4 - Beta
Classifier: Environment :: Web Environment
Classifier: Framework :: Django
Classifier: Intended Audience :: Developers
Classifier: License :: OSI Approved :: BSD License
Classifier: Operating System :: OS Independent
Classifier: Programming Language :: Python
Classifier: Topic :: Utilities
